rymovnik/__init__.py
rymovnik/rymovnik.py
rymovnik/slovnik.dic
rymovnik-0.9.7.dist-info/entry_points.txt
rymovnik-0.9.7.dist-info/LICENSE
rymovnik-0.9.7.dist-info/WHEEL
rymovnik-0.9.7.dist-info/METADATA
rymovnik-0.9.7.dist-info/RECORD
